godslayer/__init__.py
godslayer/exceptions.py
godslayer/god_slayer_factory.py
godslayer/last_line_detector.py
godslayer/line_counter.py
godslayer/list_string_matcher.py
godslayer/py.typed
godslayer/reader_operator_factory.py
godslayer/csv/__init__.py
godslayer/csv/god_slayer.py
godslayer/csv/reversed_csv_reader.py
godslayer/csv/reader_operators/__init__.py
godslayer/csv/reader_operators/header_skipper.py
godslayer/csv/reader_operators/partition_skip_record_before_footer_reader.py
godslayer/csv/reader_operators/partition_skip_record_reader.py
godslayer/csv/reader_operators/reader_operator.py
godslayer/csv/reader_operators/record_before_footer_reader.py
godslayer/csv/reader_operators/record_reader.py
godslayer-1.1.1.dist-info/licenses/LICENSE
godslayer-1.1.1.dist-info/METADATA
godslayer-1.1.1.dist-info/WHEEL
godslayer-1.1.1.dist-info/top_level.txt
godslayer-1.1.1.dist-info/RECORD
